bubblewrap.py
src/bubblewrap.py
bubblewrap_cli-1.0.0.dist-info/LICENSE
bubblewrap_cli-1.0.0.dist-info/METADATA
bubblewrap_cli-1.0.0.dist-info/WHEEL
bubblewrap_cli-1.0.0.dist-info/entry_points.txt
bubblewrap_cli-1.0.0.dist-info/top_level.txt
bubblewrap_cli-1.0.0.dist-info/RECORD
