Metadata-Version: 2.1
Name: bubblewrap-cli
Version: 1.0.0
Summary: A Python library that makes beautiful text bubbles in your terminal using NerdFont icons.
Home-page: https://github.com/TechWiz-3/bubblewrap
Author: Zac the Wise aka TechWiz-3
License-File: LICENSE
